docs/__init__.py
docs/conf.py
docs/module/__init__.py
plutonkit/__init__.py
plutonkit/command/__init__.py
plutonkit/command/action/__init__.py
plutonkit/command/action/clone_project.py
plutonkit/command/action/command.py
plutonkit/command/action/create_achitecture.py
plutonkit/command/action/create_project.py
plutonkit/command/action/help.py
plutonkit/command/action/validate_blueprint.py
plutonkit/config/__init__.py
plutonkit/config/command.py
plutonkit/config/framework.py
plutonkit/config/message.py
plutonkit/config/search.py
plutonkit/config/system.py
plutonkit/config/func/__init__.py
plutonkit/config/func/shortcut.py
plutonkit/config/func/template.py
plutonkit/framework/__init__.py
plutonkit/framework/blueprint.py
plutonkit/framework/review_blueprint.py
plutonkit/framework/starter_architecture.py
plutonkit/framework/analysis/__init__.py
plutonkit/framework/analysis/word_distance.py
plutonkit/framework/command/__init__.py
plutonkit/framework/command/schema_command.py
plutonkit/framework/command/structure_command.py
plutonkit/helper/__init__.py
plutonkit/helper/arguments.py
plutonkit/helper/command.py
plutonkit/helper/environment.py
plutonkit/helper/filesystem.py
plutonkit/helper/format.py
plutonkit/helper/template.py
plutonkit/management/__init__.py
plutonkit/management/format.py
plutonkit/management/filesystem/BlueprintFileSchema.py
plutonkit/management/filesystem/__init__.py
plutonkit/management/logic/ConditionIdentify.py
plutonkit/management/logic/ConditionSplit.py
plutonkit/management/logic/__init__.py
plutonkit/management/request/ArchitectureRequest.py
plutonkit/management/request/ValidateSource.py
plutonkit/management/request/__init__.py
plutonkit/management/template/ContentExtraction.py
plutonkit/management/template/TemplateStruct.py
plutonkit/management/template/TheShortCutWord.py
plutonkit/management/template/TheTemplate.py
plutonkit/management/template/__init__.py
plutonkit/management/terminal/__init__.py
plutonkit-1.0.31a2.dist-info/AUTHORS.md
plutonkit-1.0.31a2.dist-info/LICENSE
plutonkit-1.0.31a2.dist-info/METADATA
plutonkit-1.0.31a2.dist-info/WHEEL
plutonkit-1.0.31a2.dist-info/entry_points.txt
plutonkit-1.0.31a2.dist-info/top_level.txt
plutonkit-1.0.31a2.dist-info/RECORD
