Metadata-Version: 2.1
Name: plutonkit
Version: 1.0.31a2
Summary: Startkit for template project, for your desired structure of framework
Home-page: https://plutonkit.codehyouka.xyz/
Author: Codehyouka
Author-email: plants.coordinators@gmail.com
License: MIT
Project-URL: Documentation, https://plutonkit.codehyouka.xyz/
Project-URL: Source, https://github.com/fonipts/pluton-kit
Platform: UNKNOWN
Classifier: Development Status :: 2 - Pre-Alpha
Classifier: Environment :: Console
Classifier: Intended Audience :: Developers
Classifier: License :: OSI Approved :: MIT License
Classifier: Operating System :: OS Independent
Classifier: Programming Language :: Python
Classifier: Programming Language :: Python :: 3
Classifier: Programming Language :: Python :: 3.6
Classifier: Programming Language :: Python :: 3.7
Classifier: Programming Language :: Python :: 3.8
Classifier: Programming Language :: Python :: 3.9
Classifier: Programming Language :: Python :: 3.10
Classifier: Programming Language :: Python :: 3.11
Classifier: Programming Language :: Python :: 3.12
Requires-Python: >=3.9
License-File: LICENSE
License-File: AUTHORS.md
Requires-Dist: PyYAML
Requires-Dist: pytz
Requires-Dist: requests
